pywin_query/__init__.py
pywin_query-0.0.1.dist-info/LICENSE
pywin_query-0.0.1.dist-info/METADATA
pywin_query-0.0.1.dist-info/WHEEL
pywin_query-0.0.1.dist-info/top_level.txt
pywin_query-0.0.1.dist-info/RECORD
