Metadata-Version: 2.1
Name: pywin-query
Version: 0.0.1
Summary: An convenience wrapper that allows you to use Windows' File Search functionality.
Home-page: https://github.com/KSokhal/pywin-query
Author: KSokhal
Author-email: ksokhal99@gmail.com
License: MIT
Platform: UNKNOWN
Requires-Python: >=3.8
Requires-Dist: pywin32
